proj_haystack/__init__.py
proj_haystack/scram.py
proj_haystack/session.py
proj_haystack/utils.py
proj_haystack-0.1.3.dist-info/LICENSE
proj_haystack-0.1.3.dist-info/METADATA
proj_haystack-0.1.3.dist-info/WHEEL
proj_haystack-0.1.3.dist-info/RECORD
