Metadata-Version: 2.1
Name: proj-haystack
Version: 0.1.3
Summary: 
License: MIT
Author: Rick Jennings
Author-email: rjennings055@gmail.com
Requires-Python: >=3.10,<4.0
Classifier: License :: OSI Approved :: MIT License
Classifier: Programming Language :: Python :: 3
Classifier: Programming Language :: Python :: 3.10
Classifier: Programming Language :: Python :: 3.11
